geovoronoi/__init__.py
geovoronoi/_geom.py
geovoronoi/_voronoi.py
geovoronoi/plotting.py
geovoronoi-0.4.0.dist-info/LICENSE.txt
geovoronoi-0.4.0.dist-info/METADATA
geovoronoi-0.4.0.dist-info/WHEEL
geovoronoi-0.4.0.dist-info/top_level.txt
geovoronoi-0.4.0.dist-info/RECORD
