Metadata-Version: 2.1
Name: geovoronoi
Version: 0.4.0
Summary: a package to create and plot Voronoi regions in geographic areas
Home-page: https://github.com/WZBSocialScienceCenter/geovoronoi
Author: Markus Konrad
Author-email: markus.konrad@wzb.eu
License: Apache 2.0
Project-URL: Source, https://github.com/WZBSocialScienceCenter/geovoronoi
Project-URL: Tracker, https://github.com/WZBSocialScienceCenter/geovoronoi/issues
Keywords: voronoi tesselation gis geographic area visualization plotting
Platform: UNKNOWN
Classifier: Development Status :: 4 - Beta
Classifier: Intended Audience :: Science/Research
Classifier: Intended Audience :: Developers
Classifier: License :: OSI Approved :: Apache Software License
Classifier: Operating System :: OS Independent
Classifier: Programming Language :: Python
Classifier: Programming Language :: Python :: 3
Classifier: Programming Language :: Python :: 3.6
Classifier: Programming Language :: Python :: 3.7
Classifier: Programming Language :: Python :: 3.8
Classifier: Programming Language :: Python :: 3.9
Classifier: Programming Language :: Python :: 3.10
Classifier: Topic :: Scientific/Engineering :: Information Analysis
Classifier: Topic :: Software Development :: Libraries :: Python Modules
Classifier: Topic :: Utilities
Requires-Python: >=3.6
Provides-Extra: plotting
Provides-Extra: test
Provides-Extra: develop
Provides-Extra: all
